Workbook

Sheet Hoja 1
A2: Ingresos | G2: 70 tortas mensuales
B3: Año 1 | C3: Año 2 | D3: Año 3 | E3: Año 4 | G3: Precio de venta: aumento 15% anual
A4: Cantidades Vendidas | B4: 840 | C4: 900 | D4: 960 | E4: 1150 | G4: 0.6
A5: Precio de Venta | B5: 35000 | C5: =(B5*(1+$G$4)) -> 56000 | D5: =(C5*(1+$G$4)) -> 89600 | E5: =(D5*(1+$G$4)) -> 143360
A6: Total Ingreso | B6: =(B4*B5) -> 29400000 | C6: =(C4*C5) -> 50400000 | D6: =(D4*D5) -> 86016000 | E6: =(E4*E5) -> 164864000
A9: Egresos
B10: Año 1 | C10: Año 2 | D10: Año 3 | E10: Año 4 | G10: =(455000*12) -> 5460000
A11: Alquiler | B11: =-$G$10 -> -5460000 | C11: =-$G$10 -> -5460000 | D11: =-$G$10 -> -5460000 | E11: =-$G$10 -> -5460000
A12: Proveedores/Servicios | B12: -300000 | C12: -400000 | D12: -400000 | E12: -400000
A13: Sueldos | B13: =-(G13) -> -1500000 | C13: =(B13*(1+$H$13)) -> -2100000 | D13: =(C13*(1+$H$13)) -> -2940000 | E13: =(D13*(1+$H$13)) -> -4116000 | G13: =(500000+600000+400000) -> 1500000 | H13: 0.4
A14: Total Egresos anuales | B14: =SUM(B11:B13) -> -7260000 | C14: =SUM(C11:C13) -> -7960000 | D14: =SUM(D11:D13) -> -8800000 | E14: =SUM(E11:E13) -> -9976000
B17: 0 | C17: 1 | D17: 2 | E17: 3 | F17: 4
A18: II | B18: -5390000
A19: Ingresos | C19: =(B6) -> 29400000 | D19: =(C6) -> 50400000 | E19: =(D6) -> 86016000 | F19: =(E6) -> 164864000 | H19: 5390000 | I19: 4 | J19: =-(H19/I19) -> -1347500
A20: Egresos | C20: =(B14) -> -7260000 | D20: =(C14) -> -7960000 | E20: =(D14) -> -8800000 | F20: =(E14) -> -9976000
A21: UAIT | C21: =(C19+C20) -> 22140000 | D21: =(D19+D20) -> 42440000 | E21: =(E19+E20) -> 77216000 | F21: =(F19+F20) -> 154888000 | H21: 0.35
A22: Amortizaciones | C22: =(J19) -> -1347500 | D22: =(J19) -> -1347500 | E22: =(J19) -> -1347500 | F22: =(J19) -> -1347500
A23: Base imponible | C23: =(C21+C22) -> 20792500 | D23: =(D21+D22) -> 41092500 | E23: =(E21+E22) -> 75868500 | F23: =(F21+F22) -> 153540500
A24: IIGG | C24: =-(C23*$H$21) -> -7277375 | D24: =-(D23*$H$21) -> -14382375 | E24: =-(E23*$H$21) -> -26553975 | F24: =-(F23*$H$21) -> -53739175
A25: Amortizaciones | C25: =-($J$19) -> 1347500 | D25: =-($J$19) -> 1347500 | E25: =-($J$19) -> 1347500 | F25: =-($J$19) -> 1347500
A26: Capital de trabajo | B26: -1310000 | F26: =(1310000) -> 1310000
A27: FFON | C27: =(C23+C24+C25+C26) -> 14862625 | D27: =(D23+D24+D25+D26) -> 28057625 | E27: =(E23+E24+E25+E26) -> 50662025 | F27: =(F23+F24+F25+F26) -> 102458825
A28: Capital | B28: =(B41) -> 2156000
A29: Cuota de amortización | C29: =-(C41) -> -248490.87 | D29: =-C42 -> -385160.85 | E29: =-C43 -> -596999.32 | F29: =-C44 -> -925348.95
A30: Cuota de interés | C30: =-(D41) -> -1185800 | D30: =-D43 -> -837291.55 | E30: =-D43 -> -837291.55 | F30: =-D44 -> -508941.92
A31: Efecto impositivo | C31: =-(C30*$H$21) -> 415030 | D31: =-(D30*$H$21) -> 293052.04 | E31: =-(E30*$H$21) -> 293052.04 | F31: =-(F30*$H$21) -> 178129.67
A32: FFFN | B32: =(B18+B28) -> -3234000 | C32: =SUM(C29:C31) -> -1019260.9 | D32: =SUM(D29:D31) -> -929400.36 | E32: =SUM(E29:E31) -> -1141238.8 | F32: =SUM(F29:F31) -> -1256161.2
A33: FFO y FFFN | B33: =(B32) -> -3234000 | C33: =(C27+C32) -> 13843364 | D33: =(D27+D32) -> 27128225 | E33: =(E27+E32) -> 49520786 | F33: =(F27+F32) -> 1.0120266e+08
A34: FFD | B34: =B33 -> -3234000 | C34: =C33/(1+$G$34)^C17 -> 8389917.7 | D34: =D33/(1+$G$34)^D17 -> 9964453.5 | E34: =E33/(1+$G$34)^E17 -> 11023911 | F34: =F33/(1+$G$34)^F17 -> 13653883 | G34: 0.65
A35: VAN | B35: =(B34+C34+D34+E34+F34) -> 39798165
A36: TIR | B36: =IRR(B34:F34) -> 2.7417854
A37: PRD | B37: 1 año, 7 meses y 11 dias
A40: Periodo | B40: Deuda al Inicio | C40: C.de Amortiz. | D40: C. de Interes | E40: C. Total | F40: D. al cierre
A41: 1 | B41: =(H42*I42) -> 2156000 | C41: =(E41-D41) -> 248490.87 | D41: =(B41*$H$41) -> 1185800 | E41: =PMT($H$41,$H$45,-$B$41) -> 1434290.9 | F41: =(B41-C41) -> 1907509.1 | H41: 0.55
A42: 2 | B42: =(F41) -> 1907509.1 | C42: =(E42-D42) -> 385160.85 | D42: =(B42*$H$41) -> 1049130 | E42: =PMT($H$41,$H$45,-$B$41) -> 1434290.9 | F42: =(F41-C42) -> 1522348.3 | H42: 5390000 | I42: 0.4
A43: 3 | B43: =(F42) -> 1522348.3 | C43: =(E43-D43) -> 596999.32 | D43: =(B43*$H$41) -> 837291.55 | E43: =PMT($H$41,$H$45,-$B$41) -> 1434290.9 | F43: =(F42-C43) -> 925348.95 | H43: 1355020.9
A44: 4 | B44: =(F43) -> 925348.95 | C44: =(E44-D44) -> 925348.95 | D44: =(B44*$H$41) -> 508941.92 | E44: =PMT($H$41,$H$45,-$B$41) -> 1434290.9 | F44: =(F43-C44) -> -1.1641532e-10
H45: 4

Sheet Analisis de sensibilidad
A1: Flujo de fondo original
B2: Año 0 | C2: 1 | D2: 2 | E2: 3 | F2: 4
A3: II | B3: -5390000
A4: Ingresos | C4: 29400000 | D4: 50400000 | E4: 86016000 | F4: 164864000
A5: Egresos | C5: -7260000 | D5: -7960000 | E5: -8800000 | F5: -9976000
A6: UAIT | C6: 22140000 | D6: 42440000 | E6: 77216000 | F6: 154888000
A7: Amortizaciones | C7: -1347500 | D7: -1078000 | E7: -1078000 | F7: -1078000
A8: Base imponible | C8: 21062000 | D8: 41362000 | E8: 76138000 | F8: 153810000
A9: IIGG | C9: -7371700 | D9: -14476700 | E9: -26648300 | F9: -53833500
A10: Amortizaciones | C10: 1078000 | D10: 1078000 | E10: 1078000 | F10: 1078000
A11: Capital de trabajo | B11: -1310000 | F11: 1310000
A12: FFON | C12: 14768300 | D12: 27963300 | E12: 50567700 | F12: 102364500
A13: Capital | B13: 2156000
A14: Cuota de amortización | C14: -248490.87 | D14: -385160.85 | E14: -596999.32 | F14: -925348.95
A15: Cuota de interés | C15: -1185800 | D15: -837291.55 | E15: -837291.55 | F15: -508941.92
A16: Efecto impositivo | C16: 415030 | D16: 293052.04 | E16: 293052.04 | F16: 178129.67
A17: FFFN | B17: -3234000 | C17: -1019260.9 | D17: -929400.36 | E17: -1141238.8 | F17: -1256161.2
A18: FFO y FFFN | B18: -3234000 | C18: 13749039 | D18: 27033900 | E18: 49426461 | F18: 1.0110834e+08
A19: FFD | B19: -3234000 | C19: 13749039 | D19: 27033900 | E19: 49426461 | F19: 1.0110834e+08
A20: VAN
A21: TIR
A22: Variacion de los Egresos 10% aumento en Sueldos
B24: Año 0 | C24: 1 | D24: 2 | E24: 3 | F24: 4
A25: II | B25: -5390000
A26: Ingresos | C26: 29400000 | D26: 50400000 | E26: 86016000 | F26: 164864000
A27: Egresos | C27: =J32 -> -7410000 | D27: =K32 -> -8170000 | E27: =L32 -> -9094000 | F27: =M32 -> -10387600 | G27: 0.1 | I27: Egresos +10% Sueldos
A28: UAIT | C28: =C26+C27 -> 21990000 | D28: =D26+D27 -> 42230000 | E28: =E26+E27 -> 76922000 | F28: =F26+F27 -> 154476400 | J28: Año 1 | K28: Año 2 | L28: Año 3 | M28: Año 4
A29: Amortizaciones | C29: -1347500 | D29: -1347500 | E29: -1347500 | F29: -1347500 | I29: Alquiler | J29: -5460000 | K29: -5460000 | L29: -5460000 | M29: -5460000
A30: Base imponible | C30: =C28+C29 -> 20642500 | D30: =D28+D29 -> 40882500 | E30: =E28+E29 -> 75574500 | F30: =F28+F29 -> 153128900 | I30: Proveedores/Servicios | J30: -300000 | K30: -400000 | L30: -400000 | M30: -400000
A31: IIGG | C31: =-C30*$G$31 -> -7224875 | D31: =-D30*$G$31 -> -14308875 | E31: =-E30*$G$31 -> -26451075 | F31: =-F30*$G$31 -> -53595115 | G31: 0.35 | I31: Sueldos | J31: ='Hoja 1'!B13*(1+$G$27) -> -1650000 | K31: ='Hoja 1'!C13*(1+$G$27) -> -2310000 | L31: ='Hoja 1'!D13*(1+$G$27) -> -3234000 | M31: ='Hoja 1'!E13*(1+$G$27) -> -4527600
A32: Amortizaciones | C32: 1347500 | D32: 1347500 | E32: 1347500 | F32: 1347500 | I32: Total Egresos anuales | J32: =J29+J30+J31 -> -7410000 | K32: =K29+K30+K31 -> -8170000 | L32: =L29+L30+L31 -> -9094000 | M32: =M29+M30+M31 -> -10387600
A33: Capital de trabajo | B33: -1310000 | F33: 1310000
A34: FFON | C34: =C30+C31+C32 -> 14765125 | D34: =D30+D31+D32 -> 27921125 | E34: =E30+E31+E32 -> 50470925 | F34: =F30+F31+F32+F33 -> 102191285 | I34: Egresos - 10% Sueldos
A35: Capital | B35: 2156000 | J35: Año 1 | K35: Año 2 | L35: Año 3 | M35: Año 4
A36: Cuota de amortización | C36: -248490.87 | D36: -385160.85 | E36: -596999.32 | F36: -925348.95 | I36: Alquiler | J36: -5460000 | K36: -5460000 | L36: -5460000 | M36: -5460000
A37: Cuota de interés | C37: -1185800 | D37: -837291.55 | E37: -837291.55 | F37: -508941.92 | I37: Proveedores/Servicios | J37: -300000 | K37: -400000 | L37: -400000 | M37: -400000
A38: Efecto impositivo | C38: 415030 | D38: 293052.04 | E38: 293052.04 | F38: 178129.67 | I38: Sueldos | J38: ='Hoja 1'!B13*(1-$G$27) -> -1350000 | K38: ='Hoja 1'!C13*(1-$G$27) -> -1890000 | L38: ='Hoja 1'!D13*(1-$G$27) -> -2646000 | M38: ='Hoja 1'!E13*(1-$G$27) -> -3704400
A39: FFFN | B39: -3234000 | C39: -1019260.9 | D39: -929400.36 | E39: -1141238.8 | F39: -1256161.2 | I39: Total Egresos anuales | J39: =J36+J37+J38 -> -7110000 | K39: =K36+K37+K38 -> -7750000 | L39: =L36+L37+L38 -> -8506000 | M39: =M36+M37+M38 -> -9564400
A40: FFO y FFFN | B40: -3234000 | C40: =C34+C39 -> 13745864 | D40: =D34+D39 -> 26991725 | E40: =E34+E39 -> 49329686 | F40: =F34+F39 -> 1.0093512e+08
A41: FFD | B41: -3234000 | C41: =C40/(1+$G$41)^C24 -> 8330826.7 | D41: =D40/(1+$G$41)^D24 -> 9914315.8 | E41: =E40/(1+$G$41)^E24 -> 10981370 | F41: =F40/(1+$G$41)^F24 -> 13617787 | G41: 0.65
A42: VAN | B42: =B41+C41+D41+E41+F41 -> 39610300
A43: TIR | B43: =IRR(B41:F41,G41) -> 2.7251353
B45: Año 0 | C45: 1 | D45: 2 | E45: 3 | F45: 4
A46: II | B46: -5390000
A47: Ingresos | C47: 29400000 | D47: 50400000 | E47: 86016000 | F47: 164864000
A48: Egresos | C48: =J39 -> -7110000 | D48: =K39 -> -7750000 | E48: =L39 -> -8506000 | F48: =M39 -> -9564400 | G48: 0.1
A49: UAIT | C49: =C47+C48 -> 22290000 | D49: =D47+D48 -> 42650000 | E49: =E47+E48 -> 77510000 | F49: =F47+F48 -> 155299600
A50: Amortizaciones | C50: -1347500 | D50: -1347500 | E50: -1347500 | F50: -1347500
A51: Base imponible | C51: =C49+C50 -> 20942500 | D51: =D49+D50 -> 41302500 | E51: =E49+E50 -> 76162500 | F51: =F49+F50 -> 153952100 | H51: Sueldos | I51: VAN | J51: TIR | K51: Variación
A52: IIGG | C52: =-C51*$G$31 -> -7329875 | D52: =-D51*$G$31 -> -14455875 | E52: =-E51*$G$31 -> -26656875 | F52: =-F51*$G$31 -> -53883235 | H52: Aumento 10% | I52: =B42 -> 39610300 | J52: =B43 -> 2.7251353 | K52: ?
A53: Amortizaciones | C53: 1347500 | D53: 1347500 | E53: 1347500 | F53: 1347500 | H53: Inicial | I53: ='Hoja 1'!B35 -> 39798165 | J53: =B21
A54: Capital de trabajo | B54: -1310000 | F54: 1310000 | H54: Disminución 10% | I54: =B63 -> 39986030 | J54: =B64 -> 2.7584508 | K54: ?
A55: FFON | C55: =C51+C52+C53 -> 14960125 | D55: =D51+D52+D53 -> 28194125 | E55: =E51+E52+E53 -> 50853125 | F55: =F51+F52+F53+F54 -> 102726365 | H55: Variación del VAN | I55: =I54-I52 -> 375730.51
A56: Capital | B56: 2156000
A57: Cuota de amortización | C57: -248490.87 | D57: -385160.85 | E57: -596999.32 | F57: -925348.95
A58: Cuota de interés | C58: -1185800 | D58: -837291.55 | E58: -837291.55 | F58: -508941.92
A59: Efecto impositivo | C59: 415030 | D59: 293052.04 | E59: 293052.04 | F59: 178129.67
A60: FFFN | B60: -3234000 | C60: -1019260.9 | D60: -929400.36 | E60: -1141238.8 | F60: -1256161.2
A61: FFO y FFFN | B61: -3234000 | C61: =C55+C60 -> 13940864 | D61: =D55+D60 -> 27264725 | E61: =E55+E60 -> 49711886 | F61: =F55+F60 -> 1.014702e+08
A62: FFD | B62: -3234000 | C62: =C61/(1+$G$41)^C45 -> 8449008.6 | D62: =D61/(1+$G$41)^D45 -> 10014591 | E62: =E61/(1+$G$41)^E45 -> 11066452 | F62: =F61/(1+$G$41)^F45 -> 13689978
A63: VAN | B63: =B62+C62+D62+E62+F62 -> 39986030
A64: TIR | B64: =IRR(B62:F62,G41) -> 2.7584508
A69: Variacion disminucion 10% proveedores
B71: Año 0 | C71: 1 | D71: 2 | E71: 3 | F71: 4
A72: II | B72: -5390000
A73: Ingresos | C73: 29400000 | D73: 50400000 | E73: 86016000 | F73: 164864000
A74: Egresos | C74: =(I79) -> -7230000 | D74: =(J79) -> -7920000 | E74: =(K79) -> -8760000 | F74: =(L79) -> -9936000 | H74: Egresos
A75: UAIT | C75: =(C73+C74) -> 22170000 | D75: =(D73+D74) -> 42480000 | E75: =(E73+E74) -> 77256000 | F75: =(F73+F74) -> 154928000 | I75: Año 1 | J75: Año 2 | K75: Año 3 | L75: Año 4
A76: Amortizaciones | C76: -1347500 | D76: -1347500 | E76: -1347500 | F76: -1347500 | H76: Alquiler | I76: -5460000 | J76: -5460000 | K76: -5460000 | L76: -5460000
A77: Base imponible | C77: =(C75+C76) -> 20822500 | D77: =(D75+D76) -> 41132500 | E77: =(E75+E76) -> 75908500 | F77: =(F75+F76) -> 153580500 | H77: Proveedores/Servicios | I77: =-(300000-(300000*0.1)) -> -270000 | J77: =-(400000-(400000*0.1)) -> -360000 | K77: =-(400000-(400000*0.1)) -> -360000 | L77: =-(400000-(400000*0.1)) -> -360000
A78: IIGG | C78: =-PRODUCT(C77,0.35) -> -7287875 | D78: =-(D77*0.35) -> -14396375 | E78: =-(E77*0.35) -> -26567975 | F78: =-(F77*0.35) -> -53753175 | H78: Sueldos | I78: -1500000 | J78: -2100000 | K78: -2940000 | L78: -4116000
A79: Amortizaciones | C79: 1347500 | D79: 1347500 | E79: 1347500 | F79: 1347500 | H79: Total Egresos anuales | I79: =(I76+I77+I78) -> -7230000 | J79: =(J76+J77+J78) -> -7920000 | K79: =(K76+K77+K78) -> -8760000 | L79: =(L76+L77+L78) -> -9936000
A80: Capital de trabajo | B80: -1310000 | F80: 1310000
A81: FFON | C81: =(C77+C78+C79+C80) -> 14882125 | D81: =(D77+D78+D79+D80) -> 28083625 | E81: =(E77+E78+E79+E80) -> 50688025 | F81: =(F77+F78+F79+F80) -> 102484825
A82: Capital | B82: 2156000
A83: Cuota de amortización | C83: -248490.87 | D83: -385160.85 | E83: -596999.32 | F83: -925348.95
A84: Cuota de interés | C84: -1185800 | D84: -837291.55 | E84: -837291.55 | F84: -508941.92
A85: Efecto impositivo | C85: 415030 | D85: 293052.04 | E85: 293052.04 | F85: 178129.67
A86: FFFN | B86: -3234000 | C86: -1019260.9 | D86: -929400.36 | E86: -1141238.8 | F86: -1256161.2
A87: FFO y FFFN | B87: -3234000 | C87: =(C81+C86) -> 13862864 | D87: =(D81+D86) -> 27154225 | E87: =(E81+E86) -> 49546786 | F87: =(F81+F86) -> 1.0122866e+08
A88: FFD | B88: -3234000 | C88: =(C87/((1.65)^1)) -> 8401735.8 | D88: =(D87/((1.65)^2)) -> 9974003.5 | E88: =(E87/((1.65)^3)) -> 11029699 | F88: =(F87/((1.65)^4)) -> 13657391
A89: VAN | B89: =(B88+C88+D88+E88+F88) -> 39828829
A90: TIR | B90: =IRR(B88:F88,0.65) -> 2.7450316
A93: variacion aumento 10% proveedores
B94: Año 0 | C94: 1 | D94: 2 | E94: 3 | F94: 4
A95: II | B95: -5390000
A96: Ingresos | C96: 29400000 | D96: 50400000 | E96: 86016000 | F96: 164864000 | H96: Egresos
A97: Egresos | C97: -7290000 | D97: -8000000 | E97: -8840000 | F97: -10016000 | I97: Año 1 | J97: Año 2 | K97: Año 3 | L97: Año 4
A98: UAIT | C98: =(C96+C97) -> 22110000 | D98: =(D96+D97) -> 42400000 | E98: =(E96+E97) -> 77176000 | F98: =(F96+F97) -> 154848000 | H98: Alquiler | I98: -5460000 | J98: -5460000 | K98: -5460000 | L98: -5460000
A99: Amortizaciones | C99: -1347500 | D99: -1347500 | E99: -1347500 | F99: -1347500 | H99: Proveedores/Servicios | I99: =(-300000*1.1) -> -330000 | J99: =-(400000*1.1) -> -440000 | K99: =-(400000*1.1) -> -440000 | L99: =-(400000*1.1) -> -440000
A100: Base imponible | C100: =(C98+C99) -> 20762500 | D100: =(D98+D99) -> 41052500 | E100: =(E98+E99) -> 75828500 | F100: =(F98+F99) -> 153500500 | H100: Sueldos | I100: -1500000 | J100: -2100000 | K100: -2940000 | L100: -4116000
A101: IIGG | C101: =-(C100*0.35) -> -7266875 | D101: =-(D100*0.35) -> -14368375 | E101: =-(E100*0.35) -> -26539975 | F101: =-(F100*0.35) -> -53725175 | H101: Total Egresos anuales | I101: =(I98+I99+I100) -> -7290000 | J101: =(J98+J99+J100) -> -8000000 | K101: =(K98+K99+K100) -> -8840000 | L101: =(L98+L99+L100) -> -10016000
A102: Amortizaciones | C102: 1347500 | D102: 1347500 | E102: 1347500 | F102: 1347500
A103: Capital de trabajo | B103: -1310000 | F103: 1310000
A104: FFON | C104: =(C100+C101+C102+C103) -> 14843125 | D104: =(D100+D101+D102+D103) -> 28031625 | E104: =(E100+E101+E102+E103) -> 50636025 | F104: =(F100+F101+F102+F103) -> 102432825
A105: Capital | B105: 2156000
A106: Cuota de amortización | C106: -248490.87 | D106: -385160.85 | E106: -596999.32 | F106: -925348.95
A107: Cuota de interés | C107: -1185800 | D107: -837291.55 | E107: -837291.55 | F107: -508941.92
A108: Efecto impositivo | C108: 415030 | D108: 293052.04 | E108: 293052.04 | F108: 178129.67
A109: FFFN | B109: -3234000 | C109: -1019260.9 | D109: -929400.36 | E109: -1141238.8 | F109: -1256161.2
...

Sheet Cuantificaciòn de necesidades
A2: Costo | B2: 17000
A3: Unidades | B3: 1500
A4: Compras | B4: =B2*B3 -> 25500000
A6: Dias de cobro | B6: 20 | C6: CCE: | D6: =B6+B7-B8 -> 19
A7: Stock inventario | B7: 14 | D7: 360 | E7: dias
A8: Dias de pago | B8: 15
A10: Necesidad de Capital de trabajo: | C10: =B4*(D6/D7) -> 1345833.3
